baiji/__init__.py
baiji/cached_file.py
baiji/cli.py
baiji/config.py
baiji/connection.py
baiji/copy.py
baiji/exceptions.py
baiji/package_version.py
baiji/path.py
baiji/s3.py
baiji/test_config.py
baiji/test_s3.py
baiji/test_s3_cached_file.py
baiji/test_s3_path.py
baiji/test_s3_sync.py
baiji/test_s3_tempdir.py
baiji/util/__init__.py
baiji/util/console.py
baiji/util/environ.py
baiji/util/lookup.py
baiji/util/md5.py
baiji/util/munging.py
baiji/util/parallel.py
baiji/util/reachability.py
baiji/util/shutillib.py
baiji/util/tempfile.py
baiji/util/test_environ.py
baiji/util/test_md5.py
baiji/util/test_reachability.py
baiji/util/test_tempfile.py
baiji/util/testing.py
baiji/util/with_progressbar.py
baiji/util/yaml.py
baiji-2.10.0.data/scripts/s3
baiji-2.10.0.dist-info/DESCRIPTION.rst
baiji-2.10.0.dist-info/METADATA
baiji-2.10.0.dist-info/RECORD
baiji-2.10.0.dist-info/WHEEL
baiji-2.10.0.dist-info/metadata.json
baiji-2.10.0.dist-info/top_level.txt
