Metadata-Version: 2.0
Name: baiji
Version: 2.10.0
Summary: High-level Python abstraction layer for Amazon S3
Home-page: https://github.com/bodylabs/baiji
Author: Body Labs
Author-email: alex@bodylabs.com, paul.melnikow@bodylabs.com, chenyang.liu@bodylabs.com
License: MIT
Platform: UNKNOWN
Classifier: Development Status :: 4 - Beta
Classifier: Intended Audience :: Developers
Classifier: License :: OSI Approved :: Apache Software License
Classifier: Operating System :: OS Independent
Classifier: Programming Language :: Python
Requires-Dist: boto (>=2.38.0,<3)
Requires-Dist: plumbum (>=1.6.2,<2)
Requires-Dist: progressbar (<3,>=2.3)
Requires-Dist: pyspin (>=1.1.1,<2)
Requires-Dist: pyyaml (>=3.11,<4)
Requires-Dist: requests (<3,>=2.9.1)
